appstorescraper/__init__.py
appstorescraper/appstorescraper.py
appstorescraper/core/__init__.py
appstorescraper/core/applescraper.py
appstorescraper/models/__init__.py
appstorescraper/models/app.py
appstorescraper/models/rating.py
appstorescraper/models/review.py
appstorescraper/models/reviews.py
appstorescraperpy-0.1.1.dist-info/licenses/LICENSE
appstorescraperpy-0.1.1.dist-info/METADATA
appstorescraperpy-0.1.1.dist-info/WHEEL
appstorescraperpy-0.1.1.dist-info/top_level.txt
appstorescraperpy-0.1.1.dist-info/RECORD
