Metadata-Version: 2.4
Name: appstorescraperpy
Version: 0.1.1
Summary: Apple App Store Scraper written in Python
Author-email: Cristopher Casenillo <ccasenillo@gmail.com>
Maintainer-email: Cristopher Casenillo <ccasenillo@gmail.com>
License-Expression: MIT
Project-URL: Homepage, https://github.com/SpeakingStapler/appstorescraperpy
Project-URL: Bug Reports, https://github.com/SpeakingStapler/appstorescraperpy/issues
Keywords: web scraper,app store,apple,reviews,app,ratings,app store scraper
Classifier: Development Status :: 3 - Alpha
Classifier: Intended Audience :: Developers
Classifier: Topic :: Software Development :: Libraries
Classifier: Programming Language :: Python :: 3
Classifier: Programming Language :: Python :: 3.9
Classifier: Programming Language :: Python :: 3.10
Classifier: Programming Language :: Python :: 3.11
Classifier: Programming Language :: Python :: 3.12
Requires-Python: >=3.9
License-File: LICENSE
Requires-Dist: requests==2.32.5
Requires-Dist: pycountry==24.6.1
Dynamic: license-file
